{"artist": "Synthesized Artist", "auth": "Logged In", "firstName": "User", "gender": "M", "itemInSession": 45, "lastName": "Test43", "length": 216.4843672483953, "level": "paid", "location": "Vietnam", "method": "PUT", "page": "NextSong", "registration": 1541000000000, "sessionId": 164, "song": "Synthesized Song", "status": 200, "ts": 1763648306209, "userAgent": "Mozilla/5.0 (Windows NT 10.0; Win64; x64)", "userId": "10"}
{"artist": "Synthesized Artist", "auth": "Logged In", "firstName": "User", "gender": "F", "itemInSession": 16, "lastName": "Test65", "length": 115.99726762421383, "level": "free", "location": "Vietnam", "method": "PUT", "page": "NextSong", "registration": 1541000000000, "sessionId": 572, "song": "Synthesized Song", "status": 200, "ts": 1763648306209, "userAgent": "Mozilla/5.0 (Windows NT 10.0; Win64; x64)", "userId": "4"}
{"artist": "Synthesized Artist", "auth": "Logged In", "firstName": "User", "gender": "M", "itemInSession": 38, "lastName": "Test6", "length": 114.11278862585155, "level": "paid", "location": "Vietnam", "method": "PUT", "page": "NextSong", "registration": 1541000000000, "sessionId": 733, "song": "Synthesized Song", "status": 200, "ts": 1763648306209, "userAgent": "Mozilla/5.0 (Windows NT 10.0; Win64; x64)", "userId": "2"}
{"artist": "Synthesized Artist", "auth": "Logged In", "firstName": "User", "gender": "M", "itemInSession": 18, "lastName": "Test96", "length": 181.26623521797717, "level": "free", "location": "Vietnam", "method": "PUT", "page": "NextSong", "registration": 1541000000000, "sessionId": 568, "song": "Synthesized Song", "status": 200, "ts": 1763648306209, "userAgent": "Mozilla/5.0 (Windows NT 10.0; Win64; x64)", "userId": "10"}
{"artist": "Synthesized Artist", "auth": "Logged In", "firstName": "User", "gender": "M", "itemInSession": 28, "lastName": "Test23", "length": 131.2232586196186, "level": "paid", "location": "Vietnam", "method": "PUT", "page": "NextSong", "registration": 1541000000000, "sessionId": 462, "song": "Synthesized Song", "status": 200, "ts": 1763648306209, "userAgent": "Mozilla/5.0 (Windows NT 10.0; Win64; x64)", "userId": "7"}
{"artist": "Synthesized Artist", "auth": "Logged In", "firstName": "User", "gender": "F", "itemInSession": 24, "lastName": "Test30", "length": 293.3712931312649, "level": "free", "location": "Vietnam", "method": "PUT", "page": "NextSong", "registration": 1541000000000, "sessionId": 103, "song": "Synthesized Song", "status": 200, "ts": 1763648306209, "userAgent": "Mozilla/5.0 (Windows NT 10.0; Win64; x64)", "userId": "2"}
{"artist": "Synthesized Artist", "auth": "Logged In", "firstName": "User", "gender": "F", "itemInSession": 46, "lastName": "Test43", "length": 175.97182162248038, "level": "free", "location": "Vietnam", "method": "PUT", "page": "NextSong", "registration": 1541000000000, "sessionId": 723, "song": "Synthesized Song", "status": 200, "ts": 1763648306209, "userAgent": "Mozilla/5.0 (Windows NT 10.0; Win64; x64)", "userId": "1"}
{"artist": "Synthesized Artist", "auth": "Logged In", "firstName": "User", "gender": "F", "itemInSession": 33, "lastName": "Test65", "length": 139.34594547063185, "level": "paid", "location": "Vietnam", "method": "PUT", "page": "NextSong", "registration": 1541000000000, "sessionId": 867, "song": "Synthesized Song", "status": 200, "ts": 1763648306209, "userAgent": "Mozilla/5.0 (Windows NT 10.0; Win64; x64)", "userId": "18"}
{"artist": "Synthesized Artist", "auth": "Logged In", "firstName": "User", "gender": "M", "itemInSession": 18, "lastName": "Test62", "length": 216.75990729162618, "level": "paid", "location": "Vietnam", "method": "PUT", "page": "NextSong", "registration": 1541000000000, "sessionId": 215, "song": "Synthesized Song", "status": 200, "ts": 1763648306209, "userAgent": "Mozilla/5.0 (Windows NT 10.0; Win64; x64)", "userId": "6"}
{"artist": "Synthesized Artist", "auth": "Logged In", "firstName": "User", "gender": "M", "itemInSession": 50, "lastName": "Test77", "length": 253.1744811882632, "level": "paid", "location": "Vietnam", "method": "PUT", "page": "NextSong", "registration": 1541000000000, "sessionId": 176, "song": "Synthesized Song", "status": 200, "ts": 1763648306209, "userAgent": "Mozilla/5.0 (Windows NT 10.0; Win64; x64)", "userId": "2"}
{"artist": "Synthesized Artist", "auth": "Logged In", "firstName": "User", "gender": "F", "itemInSession": 20, "lastName": "Test25", "length": 225.4433276136903, "level": "paid", "location": "Vietnam", "method": "PUT", "page": "NextSong", "registration": 1541000000000, "sessionId": 848, "song": "Synthesized Song", "status": 200, "ts": 1763648306209, "userAgent": "Mozilla/5.0 (Windows NT 10.0; Win64; x64)", "userId": "4"}
{"artist": "Synthesized Artist", "auth": "Logged In", "firstName": "User", "gender": "F", "itemInSession": 21, "lastName": "Test96", "length": 182.5380907136741, "level": "free", "location": "Vietnam", "method": "PUT", "page": "NextSong", "registration": 1541000000000, "sessionId": 822, "song": "Synthesized Song", "status": 200, "ts": 1763648306209, "userAgent": "Mozilla/5.0 (Windows NT 10.0; Win64; x64)", "userId": "16"}
{"artist": "Synthesized Artist", "auth": "Logged In", "firstName": "User", "gender": "F", "itemInSession": 19, "lastName": "Test34", "length": 294.2650260903406, "level": "free", "location": "Vietnam", "method": "PUT", "page": "NextSong", "registration": 1541000000000, "sessionId": 941, "song": "Synthesized Song", "status": 200, "ts": 1763648306209, "userAgent": "Mozilla/5.0 (Windows NT 10.0; Win64; x64)", "userId": "5"}
{"artist": "Synthesized Artist", "auth": "Logged In", "firstName": "User", "gender": "M", "itemInSession": 7, "lastName": "Test43", "length": 273.50154505202056, "level": "paid", "location": "Vietnam", "method": "PUT", "page": "NextSong", "registration": 1541000000000, "sessionId": 545, "song": "Synthesized Song", "status": 200, "ts": 1763648306209, "userAgent": "Mozilla/5.0 (Windows NT 10.0; Win64; x64)", "userId": "16"}
{"artist": "Synthesized Artist", "auth": "Logged In", "firstName": "User", "gender": "F", "itemInSession": 27, "lastName": "Test67", "length": 234.29605987137248, "level": "free", "location": "Vietnam", "method": "PUT", "page": "NextSong", "registration": 1541000000000, "sessionId": 974, "song": "Synthesized Song", "status": 200, "ts": 1763648306209, "userAgent": "Mozilla/5.0 (Windows NT 10.0; Win64; x64)", "userId": "4"}
{"artist": "Synthesized Artist", "auth": "Logged In", "firstName": "User", "gender": "F", "itemInSession": 42, "lastName": "Test54", "length": 252.3580950993126, "level": "free", "location": "Vietnam", "method": "PUT", "page": "NextSong", "registration": 1541000000000, "sessionId": 191, "song": "Synthesized Song", "status": 200, "ts": 1763648306209, "userAgent": "Mozilla/5.0 (Windows NT 10.0; Win64; x64)", "userId": "10"}
{"artist": "Synthesized Artist", "auth": "Logged In", "firstName": "User", "gender": "M", "itemInSession": 43, "lastName": "Test3", "length": 255.8996950583213, "level": "paid", "location": "Vietnam", "method": "PUT", "page": "NextSong", "registration": 1541000000000, "sessionId": 144, "song": "Synthesized Song", "status": 200, "ts": 1763648306209, "userAgent": "Mozilla/5.0 (Windows NT 10.0; Win64; x64)", "userId": "6"}
{"artist": "Synthesized Artist", "auth": "Logged In", "firstName": "User", "gender": "M", "itemInSession": 7, "lastName": "Test37", "length": 170.21785010174534, "level": "paid", "location": "Vietnam", "method": "PUT", "page": "NextSong", "registration": 1541000000000, "sessionId": 835, "song": "Synthesized Song", "status": 200, "ts": 1763648306209, "userAgent": "Mozilla/5.0 (Windows NT 10.0; Win64; x64)", "userId": "16"}
{"artist": "Synthesized Artist", "auth": "Logged In", "firstName": "User", "gender": "F", "itemInSession": 12, "lastName": "Test46", "length": 171.8006328985642, "level": "free", "location": "Vietnam", "method": "PUT", "page": "NextSong", "registration": 1541000000000, "sessionId": 234, "song": "Synthesized Song", "status": 200, "ts": 1763648306210, "userAgent": "Mozilla/5.0 (Windows NT 10.0; Win64; x64)", "userId": "13"}
{"artist": "Synthesized Artist", "auth": "Logged In", "firstName": "User", "gender": "M", "itemInSession": 34, "lastName": "Test26", "length": 151.02283685467506, "level": "free", "location": "Vietnam", "method": "PUT", "page": "NextSong", "registration": 1541000000000, "sessionId": 289, "song": "Synthesized Song", "status": 200, "ts": 1763648306210, "userAgent": "Mozilla/5.0 (Windows NT 10.0; Win64; x64)", "userId": "8"}
{"artist": "Synthesized Artist", "auth": "Logged In", "firstName": "User", "gender": "M", "itemInSession": 49, "lastName": "Test49", "length": 237.30089401026152, "level": "paid", "location": "Vietnam", "method": "PUT", "page": "NextSong", "registration": 1541000000000, "sessionId": 385, "song": "Synthesized Song", "status": 200, "ts": 1763648306210, "userAgent": "Mozilla/5.0 (Windows NT 10.0; Win64; x64)", "userId": "18"}
{"artist": "Synthesized Artist", "auth": "Logged In", "firstName": "User", "gender": "F", "itemInSession": 21, "lastName": "Test30", "length": 173.26045785744608, "level": "paid", "location": "Vietnam", "method": "PUT", "page": "NextSong", "registration": 1541000000000, "sessionId": 683, "song": "Synthesized Song", "status": 200, "ts": 1763648306210, "userAgent": "Mozilla/5.0 (Windows NT 10.0; Win64; x64)", "userId": "12"}
{"artist": "Synthesized Artist", "auth": "Logged In", "firstName": "User", "gender": "M", "itemInSession": 35, "lastName": "Test72", "length": 134.29777711757163, "level": "paid", "location": "Vietnam", "method": "PUT", "page": "NextSong", "registration": 1541000000000, "sessionId": 827, "song": "Synthesized Song", "status": 200, "ts": 1763648306210, "userAgent": "Mozilla/5.0 (Windows NT 10.0; Win64; x64)", "userId": "2"}
{"artist": "Synthesized Artist", "auth": "Logged In", "firstName": "User", "gender": "M", "itemInSession": 16, "lastName": "Test92", "length": 174.97664638217867, "level": "free", "location": "Vietnam", "method": "PUT", "page": "NextSong", "registration": 1541000000000, "sessionId": 816, "song": "Synthesized Song", "status": 200, "ts": 1763648306210, "userAgent": "Mozilla/5.0 (Windows NT 10.0; Win64; x64)", "userId": "8"}
{"artist": "Synthesized Artist", "auth": "Logged In", "firstName": "User", "gender": "M", "itemInSession": 14, "lastName": "Test50", "length": 142.92206747960853, "level": "free", "location": "Vietnam", "method": "PUT", "page": "NextSong", "registration": 1541000000000, "sessionId": 523, "song": "Synthesized Song", "status": 200, "ts": 1763648306210, "userAgent": "Mozilla/5.0 (Windows NT 10.0; Win64; x64)", "userId": "4"}
{"artist": "Synthesized Artist", "auth": "Logged In", "firstName": "User", "gender": "M", "itemInSession": 47, "lastName": "Test88", "length": 158.87953578334674, "level": "paid", "location": "Vietnam", "method": "PUT", "page": "NextSong", "registration": 1541000000000, "sessionId": 617, "song": "Synthesized Song", "status": 200, "ts": 1763648306210, "userAgent": "Mozilla/5.0 (Windows NT 10.0; Win64; x64)", "userId": "14"}
{"artist": "Synthesized Artist", "auth": "Logged In", "firstName": "User", "gender": "M", "itemInSession": 5, "lastName": "Test30", "length": 263.594756764915, "level": "paid", "location": "Vietnam", "method": "PUT", "page": "NextSong", "registration": 1541000000000, "sessionId": 387, "song": "Synthesized Song", "status": 200, "ts": 1763648306210, "userAgent": "Mozilla/5.0 (Windows NT 10.0; Win64; x64)", "userId": "1"}
{"artist": "Synthesized Artist", "auth": "Logged In", "firstName": "User", "gender": "F", "itemInSession": 37, "lastName": "Test55", "length": 290.48094712619024, "level": "paid", "location": "Vietnam", "method": "PUT", "page": "NextSong", "registration": 1541000000000, "sessionId": 941, "song": "Synthesized Song", "status": 200, "ts": 1763648306210, "userAgent": "Mozilla/5.0 (Windows NT 10.0; Win64; x64)", "userId": "16"}
{"artist": "Synthesized Artist", "auth": "Logged In", "firstName": "User", "gender": "M", "itemInSession": 34, "lastName": "Test67", "length": 186.05371306473364, "level": "free", "location": "Vietnam", "method": "PUT", "page": "NextSong", "registration": 1541000000000, "sessionId": 893, "song": "Synthesized Song", "status": 200, "ts": 1763648306210, "userAgent": "Mozilla/5.0 (Windows NT 10.0; Win64; x64)", "userId": "15"}
{"artist": "Synthesized Artist", "auth": "Logged In", "firstName": "User", "gender": "M", "itemInSession": 11, "lastName": "Test70", "length": 203.2411689306033, "level": "free", "location": "Vietnam", "method": "PUT", "page": "NextSong", "registration": 1541000000000, "sessionId": 952, "song": "Synthesized Song", "status": 200, "ts": 1763648306210, "userAgent": "Mozilla/5.0 (Windows NT 10.0; Win64; x64)", "userId": "15"}
{"artist": "Synthesized Artist", "auth": "Logged In", "firstName": "User", "gender": "F", "itemInSession": 19, "lastName": "Test93", "length": 140.55381474605156, "level": "paid", "location": "Vietnam", "method": "PUT", "page": "NextSong", "registration": 1541000000000, "sessionId": 122, "song": "Synthesized Song", "status": 200, "ts": 1763648306210, "userAgent": "Mozilla/5.0 (Windows NT 10.0; Win64; x64)", "userId": "7"}
{"artist": "Synthesized Artist", "auth": "Logged In", "firstName": "User", "gender": "F", "itemInSession": 23, "lastName": "Test5", "length": 217.0349785413753, "level": "paid", "location": "Vietnam", "method": "PUT", "page": "NextSong", "registration": 1541000000000, "sessionId": 477, "song": "Synthesized Song", "status": 200, "ts": 1763648306210, "userAgent": "Mozilla/5.0 (Windows NT 10.0; Win64; x64)", "userId": "14"}
{"artist": "Synthesized Artist", "auth": "Logged In", "firstName": "User", "gender": "M", "itemInSession": 3, "lastName": "Test22", "length": 297.0924882525243, "level": "paid", "location": "Vietnam", "method": "PUT", "page": "NextSong", "registration": 1541000000000, "sessionId": 818, "song": "Synthesized Song", "status": 200, "ts": 1763648306210, "userAgent": "Mozilla/5.0 (Windows NT 10.0; Win64; x64)", "userId": "18"}
{"artist": "Synthesized Artist", "auth": "Logged In", "firstName": "User", "gender": "F", "itemInSession": 23, "lastName": "Test23", "length": 192.97241898134376, "level": "free", "location": "Vietnam", "method": "PUT", "page": "NextSong", "registration": 1541000000000, "sessionId": 452, "song": "Synthesized Song", "status": 200, "ts": 1763648306210, "userAgent": "Mozilla/5.0 (Windows NT 10.0; Win64; x64)", "userId": "7"}
{"artist": "Synthesized Artist", "auth": "Logged In", "firstName": "User", "gender": "F", "itemInSession": 18, "lastName": "Test63", "length": 204.91736199311075, "level": "free", "location": "Vietnam", "method": "PUT", "page": "NextSong", "registration": 1541000000000, "sessionId": 181, "song": "Synthesized Song", "status": 200, "ts": 1763648306210, "userAgent": "Mozilla/5.0 (Windows NT 10.0; Win64; x64)", "userId": "4"}
{"artist": "Synthesized Artist", "auth": "Logged In", "firstName": "User", "gender": "M", "itemInSession": 27, "lastName": "Test84", "length": 145.91560009892353, "level": "paid", "location": "Vietnam", "method": "PUT", "page": "NextSong", "registration": 1541000000000, "sessionId": 619, "song": "Synthesized Song", "status": 200, "ts": 1763648306210, "userAgent": "Mozilla/5.0 (Windows NT 10.0; Win64; x64)", "userId": "19"}
{"artist": "Synthesized Artist", "auth": "Logged In", "firstName": "User", "gender": "F", "itemInSession": 0, "lastName": "Test78", "length": 274.61145126051383, "level": "paid", "location": "Vietnam", "method": "PUT", "page": "NextSong", "registration": 1541000000000, "sessionId": 891, "song": "Synthesized Song", "status": 200, "ts": 1763648306210, "userAgent": "Mozilla/5.0 (Windows NT 10.0; Win64; x64)", "userId": "4"}
{"artist": "Synthesized Artist", "auth": "Logged In", "firstName": "User", "gender": "M", "itemInSession": 37, "lastName": "Test70", "length": 103.42316432056948, "level": "free", "location": "Vietnam", "method": "PUT", "page": "NextSong", "registration": 1541000000000, "sessionId": 255, "song": "Synthesized Song", "status": 200, "ts": 1763648306210, "userAgent": "Mozilla/5.0 (Windows NT 10.0; Win64; x64)", "userId": "7"}
{"artist": "Synthesized Artist", "auth": "Logged In", "firstName": "User", "gender": "M", "itemInSession": 8, "lastName": "Test79", "length": 257.19708957359774, "level": "paid", "location": "Vietnam", "method": "PUT", "page": "NextSong", "registration": 1541000000000, "sessionId": 639, "song": "Synthesized Song", "status": 200, "ts": 1763648306210, "userAgent": "Mozilla/5.0 (Windows NT 10.0; Win64; x64)", "userId": "5"}
{"artist": "Synthesized Artist", "auth": "Logged In", "firstName": "User", "gender": "F", "itemInSession": 10, "lastName": "Test43", "length": 208.14343669173397, "level": "free", "location": "Vietnam", "method": "PUT", "page": "NextSong", "registration": 1541000000000, "sessionId": 920, "song": "Synthesized Song", "status": 200, "ts": 1763648306210, "userAgent": "Mozilla/5.0 (Windows NT 10.0; Win64; x64)", "userId": "20"}
{"artist": "Synthesized Artist", "auth": "Logged In", "firstName": "User", "gender": "M", "itemInSession": 22, "lastName": "Test84", "length": 186.8767018136826, "level": "paid", "location": "Vietnam", "method": "PUT", "page": "NextSong", "registration": 1541000000000, "sessionId": 786, "song": "Synthesized Song", "status": 200, "ts": 1763648306210, "userAgent": "Mozilla/5.0 (Windows NT 10.0; Win64; x64)", "userId": "6"}
{"artist": "Synthesized Artist", "auth": "Logged In", "firstName": "User", "gender": "M", "itemInSession": 38, "lastName": "Test89", "length": 124.69829209426695, "level": "paid", "location": "Vietnam", "method": "PUT", "page": "NextSong", "registration": 1541000000000, "sessionId": 107, "song": "Synthesized Song", "status": 200, "ts": 1763648306210, "userAgent": "Mozilla/5.0 (Windows NT 10.0; Win64; x64)", "userId": "10"}
{"artist": "Synthesized Artist", "auth": "Logged In", "firstName": "User", "gender": "F", "itemInSession": 32, "lastName": "Test34", "length": 131.4610894730351, "level": "free", "location": "Vietnam", "method": "PUT", "page": "NextSong", "registration": 1541000000000, "sessionId": 355, "song": "Synthesized Song", "status": 200, "ts": 1763648306210, "userAgent": "Mozilla/5.0 (Windows NT 10.0; Win64; x64)", "userId": "15"}
{"artist": "Synthesized Artist", "auth": "Logged In", "firstName": "User", "gender": "M", "itemInSession": 10, "lastName": "Test100", "length": 187.22123156964676, "level": "paid", "location": "Vietnam", "method": "PUT", "page": "NextSong", "registration": 1541000000000, "sessionId": 266, "song": "Synthesized Song", "status": 200, "ts": 1763648306210, "userAgent": "Mozilla/5.0 (Windows NT 10.0; Win64; x64)", "userId": "1"}
{"artist": "Synthesized Artist", "auth": "Logged In", "firstName": "User", "gender": "M", "itemInSession": 11, "lastName": "Test98", "length": 197.03435640218675, "level": "free", "location": "Vietnam", "method": "PUT", "page": "NextSong", "registration": 1541000000000, "sessionId": 311, "song": "Synthesized Song", "status": 200, "ts": 1763648306210, "userAgent": "Mozilla/5.0 (Windows NT 10.0; Win64; x64)", "userId": "10"}
{"artist": "Synthesized Artist", "auth": "Logged In", "firstName": "User", "gender": "M", "itemInSession": 12, "lastName": "Test21", "length": 248.28684582636805, "level": "free", "location": "Vietnam", "method": "PUT", "page": "NextSong", "registration": 1541000000000, "sessionId": 581, "song": "Synthesized Song", "status": 200, "ts": 1763648306210, "userAgent": "Mozilla/5.0 (Windows NT 10.0; Win64; x64)", "userId": "2"}
{"artist": "Synthesized Artist", "auth": "Logged In", "firstName": "User", "gender": "M", "itemInSession": 21, "lastName": "Test27", "length": 241.90231827479633, "level": "paid", "location": "Vietnam", "method": "PUT", "page": "NextSong", "registration": 1541000000000, "sessionId": 304, "song": "Synthesized Song", "status": 200, "ts": 1763648306210, "userAgent": "Mozilla/5.0 (Windows NT 10.0; Win64; x64)", "userId": "14"}
{"artist": "Synthesized Artist", "auth": "Logged In", "firstName": "User", "gender": "F", "itemInSession": 23, "lastName": "Test62", "length": 184.89963098858976, "level": "free", "location": "Vietnam", "method": "PUT", "page": "NextSong", "registration": 1541000000000, "sessionId": 945, "song": "Synthesized Song", "status": 200, "ts": 1763648306210, "userAgent": "Mozilla/5.0 (Windows NT 10.0; Win64; x64)", "userId": "14"}
{"artist": "Synthesized Artist", "auth": "Logged In", "firstName": "User", "gender": "F", "itemInSession": 48, "lastName": "Test52", "length": 238.93731623790174, "level": "free", "location": "Vietnam", "method": "PUT", "page": "NextSong", "registration": 1541000000000, "sessionId": 751, "song": "Synthesized Song", "status": 200, "ts": 1763648306210, "userAgent": "Mozilla/5.0 (Windows NT 10.0; Win64; x64)", "userId": "20"}
{"artist": "Synthesized Artist", "auth": "Logged In", "firstName": "User", "gender": "M", "itemInSession": 1, "lastName": "Test29", "length": 228.54929712271363, "level": "free", "location": "Vietnam", "method": "PUT", "page": "NextSong", "registration": 1541000000000, "sessionId": 897, "song": "Synthesized Song", "status": 200, "ts": 1763648306210, "userAgent": "Mozilla/5.0 (Windows NT 10.0; Win64; x64)", "userId": "19"}
